shoonya/__init__.py
shoonya/exceptions.py
shoonya/shoonya.py
shoonya-0.1.3.dist-info/LICENSE
shoonya-0.1.3.dist-info/WHEEL
shoonya-0.1.3.dist-info/METADATA
shoonya-0.1.3.dist-info/RECORD
